pyspec2openapi/__init__.py
pyspec2openapi/__main__.py
pyspec2openapi/index.py
pyspec2openapi/tests/__init__.py
pyspec2openapi/tests/test_index.py
pyspec2openapi-0.3.0.dist-info/METADATA
pyspec2openapi-0.3.0.dist-info/WHEEL
pyspec2openapi-0.3.0.dist-info/entry_points.txt
pyspec2openapi-0.3.0.dist-info/RECORD
