Metadata-Version: 2.1
Name: pyspec2openapi
Version: 0.3.0
Summary: Convert Ethereum consensus spec SSZ types to OpenAPI type schema definitions
Author: dapplion
Author-email: 35266934+dapplion@users.noreply.github.com
Requires-Python: >=3.8,<4.0
Classifier: Programming Language :: Python :: 3
Classifier: Programming Language :: Python :: 3.8
Classifier: Programming Language :: Python :: 3.9
Classifier: Programming Language :: Python :: 3.10
Classifier: Programming Language :: Python :: 3.11
Classifier: Programming Language :: Python :: 3.12
Requires-Dist: deepmerge (>=1.1.1,<2.0.0)
Requires-Dist: pyyaml (>=6.0.1,<7.0.0)
Requires-Dist: requests (>=2.31.0,<3.0.0)
Requires-Dist: types-pyyaml (>=6.0.12.12,<7.0.0.0)
Requires-Dist: types-requests (>=2.31.0.20240106,<3.0.0.0)
